my_meter_api/MyMeterApi.py
my_meter_api/__init__.py
my_meter_api/error.py
my_meter_api/util.py
my_meter_api-0.2.0.dist-info/METADATA
my_meter_api-0.2.0.dist-info/WHEEL
my_meter_api-0.2.0.dist-info/licenses/LICENSE
my_meter_api-0.2.0.dist-info/RECORD
