Metadata-Version: 2.4
Name: my-meter-api
Version: 0.2.0
Summary: Get your electricity meter reading and usage data from compatible MyMeter sites.
Author-email: Tag Howard <tag@jthoward.dev>
License-Expression: MIT
License-File: LICENSE
Classifier: Operating System :: OS Independent
Classifier: Programming Language :: Python :: 3
Requires-Python: >=3.13
Requires-Dist: requests>=2.32.3
